{"version":4,"duration":1878998,"pause":2,"calories":405,"dehydration_volume":604,"plausible":true,"start_time_timezone_offset":-10800000,"end_time_timezone_offset":-10800000,"tracking_method":"tracked","start_time":1691100365000,"end_time":1691102244000,"user_perceived_start_time":1691089565000,"user_perceived_end_time":1691091444000,"created_at":1691102251000,"updated_at":1718039439835,"features":[{"type":"weather","attributes":{"conditions":"night","temperature":19.0,"wind_speed":"1.6666666666666665","wind_direction":110.0,"humidity":73.0}},{"type":"map","attributes":{"encoded_trace":"fj~eDr|{dI??VvAf@jA^hA`@hAp@lAExAG`BNj@XzAf@pAvAB`BSz@G~@M|AGjBK|AEfADpAf@xA`@vAh@bBb@xAd@~Af@zAB`B@`B?~AEvAi@|Aa@pAa@tAJrAJjAFfAHtALrAErAOjAQhAOhAa@rASvA_@tAa@tAc@xAc@rAe@vAm@bA]m@JeA^wAh@yAf@yAb@}Ad@{A`@{Ab@_B\\_BP{AR}AN}AG_BM_BM{AK}ACuAj@}Ah@}@X_BBqAAwAAuA?wASuAi@aBi@wAg@wA]kAa@`@Pt@PvAf@bBd@xAd@vA`@bBZ~A@hB?~A@xAa@bBc@?GyAj@uAZmB?eBCeB?cBYaBg@}Ag@aBc@_Bo@yAe@u@Q??","trace_available":true,"start_latitude":"-27.357961654663086","start_longitude":"-53.396095275878906"}},{"type":"track_metrics","attributes":{"distance":5194,"average_speed":2.76423923814714,"average_pace":"0.36176318829418563","max_speed":3.554995324876573,"elevation_gain":922,"elevation_loss":835}},{"type":"fastest_segments","attributes":{"segments":[{"distance":"1km","duration":324388,"started_at":1691101878164},{"distance":"1mi","duration":549780,"started_at":1691101670156},{"distance":"3mi","duration":1725779,"started_at":1691100494161},{"distance":"5km","duration":1796803,"started_at":1691100406153}]}},{"type":"steps","attributes":{"average_step_rate":144,"maximum_step_rate":160,"total_steps":4525,"average_step_length":114}},{"type":"equipment","attributes":{"user_equipment":[{"id":"63a754ccee56bf08a2ad1204","type":"user_equipment_shoe"}]}},{"type":"initial_values","attributes":{"distance":5194,"duration":1878998,"pause":2,"sport_type":{"id":"1","type":"sport_type"},"start_time":1691100365000,"end_time":1691102244000}},{"type":"origin","attributes":{"device":{"name":"iPhone12,8","vendor":"Apple","os_version":"iOS 16.5.1"}}}],"id":"320ce1f5-5871-4d84-b2eb-e40bbd113b78","user_id":"E3SJP52HCFA1QS54","sport_type_id":"1","creation_application_id":"3186"}