{"version":5,"duration":1713982,"pause":18,"calories":396,"dehydration_volume":588,"plausible":true,"start_time_timezone_offset":-10800000,"end_time_timezone_offset":-10800000,"tracking_method":"tracked","start_time":1687814481000,"end_time":1687816195000,"user_perceived_start_time":1687803681000,"user_perceived_end_time":1687805395000,"created_at":1687816201000,"updated_at":1718039452667,"features":[{"type":"weather","attributes":{"conditions":"night","temperature":19.0,"wind_speed":"1.6666666666666665","wind_direction":0.0,"humidity":74.0}},{"type":"map","attributes":{"encoded_trace":"ng_fDts|dI??jAj@nAZpAb@lA^tAb@pAd@`BT|A@zA@|AArAQtAg@vA]lAY~ANnAJjAJnAFxAJxAQpAOnAOpAa@tAW|Ae@zA_@tAa@tA_@tAk@~Am@nAc@sAb@}Aj@yAh@}Ab@_Bd@wAh@cAL}Ad@}AV}AN}AVcBA}AIqAGmBSaBK_B`@{An@uAb@oAFwAC_CGqBSeBk@gBk@cBc@eBs@eAO`Bj@|Ah@bBb@~Af@~Aj@rBJjBAfBF`AAdBo@`Bg@xAa@~ANtANlAFrAHYE}ASeBMaBMaBPaBp@{Al@sADcB?gBCgBCcBi@oA_@cBk@aBi@aBe@qAU}AA_BNs@P","trace_available":true,"start_latitude":"-27.362642288208008","start_longitude":-53.3997917175293}},{"type":"track_metrics","attributes":{"distance":5015,"average_speed":"2.9259350448254415","average_pace":0.3417710867397807,"max_speed":3.669336636861165,"elevation_gain":942,"elevation_loss":956}},{"type":"fastest_segments","attributes":{"segments":[{"distance":"1km","duration":310114,"started_at":1687815433962},{"distance":"1mi","duration":516929,"started_at":1687815173955},{"distance":"3mi","duration":1640906,"started_at":1687814543848},{"distance":"5km","duration":1707163,"started_at":1687814482116}]}},{"type":"steps","attributes":{"average_step_rate":147,"maximum_step_rate":160,"total_steps":4193,"average_step_length":119}},{"type":"equipment","attributes":{"user_equipment":[{"id":"63a754ccee56bf08a2ad1204","type":"user_equipment_shoe"}]}},{"type":"initial_values","attributes":{"distance":5015,"duration":1713982,"pause":18,"sport_type":{"id":"1","type":"sport_type"},"start_time":1687814481000,"end_time":1687816195000}},{"type":"origin","attributes":{"device":{"name":"iPhone12,8","vendor":"Apple","os_version":"iOS 16.5.1"}}}],"id":"fa5524ad-3e10-46a5-9389-aa828066b11a","user_id":"E3SJP52HCFA1QS54","sport_type_id":"1","creation_application_id":"3178"}