{"version":4,"duration":2910000,"pause":0,"calories":635,"subjective_feeling":"awesome","dehydration_volume":925,"plausible":true,"start_time_timezone_offset":-10800000,"end_time_timezone_offset":-10800000,"tracking_method":"tracked","start_time":1661379553000,"end_time":1661382463000,"user_perceived_start_time":1661368753000,"user_perceived_end_time":1661371663000,"created_at":1661382468000,"updated_at":1718039524507,"features":[{"type":"weather","attributes":{"conditions":"night","temperature":18.0,"wind_speed":"2.2222222222222223","wind_direction":110.0,"humidity":74.0}},{"type":"map","attributes":{"encoded_trace":"zm~eDve|dI??jAtBYzCf@jCxA|AzCUlCGxCa@zCCdC`AlCx@rCz@tCx@`D@dDBrCu@lC}@nCH`CNbCTfCG~BY~Bg@~Bk@pCs@jC}@nC{@dC_A_Ct@sC~@uCz@mCt@wCx@yC^oC\\_DQ_DY_DGwCdAwCn@_DG_DA}CaAyC}@}CiAj@\\tC|@xC~@vCr@|CD|CBrCy@jC{@jCHzBNbCR~BAvBWtBWxBk@dCs@lCw@jCw@jCeAU@iC`AkCx@oCt@oCr@oCl@wC^{CLyBSwCUyCAoCfAsCj@wCMuCBsC{@kCy@gC{@sA[nC|@pCz@jCx@xC\\dC@bCDrC_AFAoCz@yCCsC@uCg@kC}@iCy@mAg@","trace_available":true,"start_latitude":"-27.358539581298828","start_longitude":"-53.397560119628906"}},{"type":"track_metrics","attributes":{"distance":8003,"average_speed":2.750171821305842,"average_pace":"0.36361364488316883","max_speed":"3.3501839637756348","elevation_gain":1404,"elevation_loss":1424,"surface":"road"}},{"type":"fastest_segments","attributes":{"segments":[{"distance":"1km","duration":334081,"started_at":1661380540149},{"distance":"1mi","duration":543175,"started_at":1661380552161},{"distance":"3mi","duration":1736722,"started_at":1661380386159},{"distance":"5km","duration":1800729,"started_at":1661380292156}]}},{"type":"steps","attributes":{"average_step_rate":144,"maximum_step_rate":155,"total_steps":7021,"average_step_length":113}},{"type":"equipment","attributes":{"user_equipment":[{"id":"6182f862c20fc2a3f2c06146","type":"user_equipment_shoe"}]}},{"type":"initial_values","attributes":{"distance":8003,"duration":2910000,"pause":0,"sport_type":{"id":"1","type":"sport_type"},"start_time":1661379553000,"end_time":1661382463000}},{"type":"origin","attributes":{"device":{"name":"iPhone12,8","vendor":"Apple","os_version":"iOS 15.6.1"}}}],"id":"d548d270-ad9f-4633-86f3-be003f7facc9","user_id":"E3SJP52HCFA1QS54","sport_type_id":"1","creation_application_id":"3063"}