{"version":4,"duration":1711000,"pause":0,"calories":375,"dehydration_volume":674,"plausible":true,"start_time_timezone_offset":-10800000,"end_time_timezone_offset":-10800000,"tracking_method":"tracked","start_time":1703440993000,"end_time":1703442704000,"user_perceived_start_time":1703430193000,"user_perceived_end_time":1703431904000,"created_at":1703442709000,"updated_at":1718039403507,"features":[{"type":"weather","attributes":{"conditions":"cloudy","temperature":28.0,"wind_speed":"2.2222222222222223","wind_direction":260.0,"humidity":67.0}},{"type":"map","attributes":{"encoded_trace":"ji~eDv|{dI??r@jAl@nAP|Ab@hAv@vAOjBKnAd@nAp@vAxA`@zASlAYtABbBU|AG|AE|@TzAd@tAd@xAd@xAb@vAd@xA`@|A@~AB|A?dBGtAk@xAe@vA]tAJnAHpAL~AH~AHrAKhAOlAMhASvA[xAe@~Ac@~Ae@~Aa@xAi@xAm@`A_@e@NyAh@eBr@iBf@aBd@eBf@gBf@yA^}ARaBP_BPiBGcBOaBKcBMeAAgAb@gBh@}Ah@eBEiB?iBCeBY}Ag@cBk@cBk@eBg@w@Sn@Rz@TfBj@~Ad@`Bj@bBf@dBBhB@lBBnBWzAk@n@S{Aj@iBn@eB?kBCeBAmBWaBi@iA]","trace_available":true,"start_latitude":-27.35782241821289,"start_longitude":"-53.396121978759766"}},{"type":"track_metrics","attributes":{"distance":5007,"average_speed":"2.9263588544710695","average_pace":"0.34172158977431594","max_speed":"3.7890113724602594","elevation_gain":733,"elevation_loss":951}},{"type":"fastest_segments","attributes":{"segments":[{"distance":"1km","duration":313078,"started_at":1703442386044},{"distance":"1mi","duration":522732,"started_at":1703442174044},{"distance":"3mi","duration":1642715,"started_at":1703441054047},{"distance":"5km","duration":1705846,"started_at":1703440994030}]}},{"type":"steps","attributes":{"average_step_rate":146,"maximum_step_rate":160,"total_steps":4187,"average_step_length":119}},{"type":"equipment","attributes":{"user_equipment":[{"id":"650cceddbe4fa8e8c5e49787","type":"user_equipment_shoe"}]}},{"type":"initial_values","attributes":{"distance":5007,"duration":1711000,"pause":0,"sport_type":{"id":"1","type":"sport_type"},"start_time":1703440993000,"end_time":1703442704000}},{"type":"origin","attributes":{"device":{"name":"iPhone14,4","vendor":"Apple","os_version":"iOS 17.1.2"}}}],"id":"75150b50-1c57-4205-a408-46d50791fe08","user_id":"E3SJP52HCFA1QS54","sport_type_id":"1","creation_application_id":"3221"}